llama_index/readers/mondaydotcom/__init__.py
llama_index/readers/mondaydotcom/base.py
llama_index_readers_mondaydotcom-0.4.1.dist-info/METADATA
llama_index_readers_mondaydotcom-0.4.1.dist-info/WHEEL
llama_index_readers_mondaydotcom-0.4.1.dist-info/licenses/LICENSE
llama_index_readers_mondaydotcom-0.4.1.dist-info/RECORD
