Metadata-Version: 2.4
Name: llama-index-readers-mondaydotcom
Version: 0.4.1
Summary: llama-index readers mondaydotcom integration
Author-email: Your Name <you@example.com>
Maintainer: nadavgr
License-Expression: MIT
License-File: LICENSE
Keywords: monday,mondaydotcom
Requires-Python: <4.0,>=3.9
Requires-Dist: llama-index-core<0.15,>=0.13.0
Requires-Dist: requests<3,>=2.31.0
